viber_botapi/__init__.py
viber_botapi/bot.py
viber_botapi/types/__init__.py
viber_botapi/types/base.py
viber_botapi/types/button.py
viber_botapi/types/contact.py
viber_botapi/types/contact_message.py
viber_botapi/types/favorites_metadata.py
viber_botapi/types/file_message.py
viber_botapi/types/frame.py
viber_botapi/types/internal_browser.py
viber_botapi/types/keyboard.py
viber_botapi/types/location.py
viber_botapi/types/location_message.py
viber_botapi/types/map.py
viber_botapi/types/media_player.py
viber_botapi/types/message.py
viber_botapi/types/picture_message.py
viber_botapi/types/rich_media.py
viber_botapi/types/rich_media_message.py
viber_botapi/types/sender.py
viber_botapi/types/sticker_message.py
viber_botapi/types/text_message.py
viber_botapi/types/url_message.py
viber_botapi/types/video_message.py
viber_botapi/types/webhook.py
viber_botapi/utils/__init__.py
viber_botapi/utils/constants.py
viber_botapi/utils/exceptions.py
viber_botapi/utils/log.py
viber_botapi-1.0.1.dist-info/LICENSE.txt
viber_botapi-1.0.1.dist-info/METADATA
viber_botapi-1.0.1.dist-info/WHEEL
viber_botapi-1.0.1.dist-info/top_level.txt
viber_botapi-1.0.1.dist-info/RECORD
