Metadata-Version: 2.1
Name: viber-botapi
Version: 1.0.1
Summary: Python api to Viber and async bot
Home-page: https://github.com/EdiBoba/viber-botapi
Author: Vyacheslav Rineisky
Author-email: rineisky@gmail.com
License: Apache 2.0
Platform: UNKNOWN
Classifier: Development Status :: 5 - Production/Stable
Classifier: Framework :: AsyncIO
Classifier: Intended Audience :: Developers
Classifier: Intended Audience :: System Administrators
Classifier: Programming Language :: Python :: 3.7
Classifier: Programming Language :: Python :: 3.8
Classifier: Programming Language :: Python :: 3.9
Classifier: License :: OSI Approved :: Apache Software License
Classifier: Topic :: Software Development :: Libraries :: Application Frameworks
Classifier: Operating System :: OS Independent
Requires-Dist: botapi (>=1.1.0)
Provides-Extra: bot
Requires-Dist: aiohttp ; extra == 'bot'
